Metadata-Version: 2.1
Name: certbot-dns-vultr
Version: 1.1.0
Summary: Vultr DNS authenticator plugin for Certbot
Home-page: https://github.com/lezgomatt/certbot-dns-vultr
Author: Matt
Author-email: lezgomatt@gmail.com
License: Zlib
Classifier: Development Status :: 5 - Production/Stable
Classifier: Environment :: Plugins
Classifier: Intended Audience :: System Administrators
Classifier: License :: OSI Approved :: zlib/libpng License
Classifier: Operating System :: POSIX :: Linux
Classifier: Programming Language :: Python
Classifier: Programming Language :: Python :: 3
Classifier: Programming Language :: Python :: 3 :: Only
Classifier: Topic :: Internet :: WWW/HTTP
Classifier: Topic :: Security
Classifier: Topic :: System :: Installation/Setup
Classifier: Topic :: System :: Networking
Classifier: Topic :: System :: Systems Administration
Classifier: Topic :: Utilities
Requires-Python: >=3.6
License-File: LICENSE
Requires-Dist: certbot
Requires-Dist: requests
Requires-Dist: zope.interface
